cms_model/__init__.py
cms_model/cms_model.py
cms_model-0.1.0.dist-info/LICENSE.txt
cms_model-0.1.0.dist-info/METADATA
cms_model-0.1.0.dist-info/WHEEL
cms_model-0.1.0.dist-info/top_level.txt
cms_model-0.1.0.dist-info/RECORD
