Metadata-Version: 2.1
Name: cms_model
Version: 0.1.0
Summary: Coordinated Minima Search: An Efficient Approach for Optimizing Linear and Non-Linear Regression Models.
Home-page: https://github.com/RHassan1609/cms.git
Author: Rifat Hassan
Author-email: h.rifat1609@gmail.com
License: MIT
Classifier: Programming Language :: Python :: 3
Classifier: License :: OSI Approved :: MIT License
Classifier: Operating System :: OS Independent
Requires-Python: >=3.6
License-File: LICENSE.txt
